[
  {
    "_id": "58c665588b6aa52311afa02d",
    "name_one": "1-к.кв",
    "name": "1-к.кв",
    "crm_id": 1
  },
  {
    "_id": "58c665588b6aa52311afa034",
    "name_one": "2Е-к.кв",
    "name": "2Е-к.кв",
    "crm_id": 22
  },
  {
    "_id": "58c665588b6aa52311afa03a",
    "name_one": "К. пом",
    "name": "К. пом",
    "crm_id": 50
  },
  {
    "_id": "6423fe037f8ed055120cf0be",
    "crm_id": 1001,
    "name": "Студии",
    "name_one": "Студия"
  },
  {
    "_id": "58c665588b6aa52311afa02e",
    "name_one": "2-к.кв",
    "name": "2-к.кв",
    "crm_id": 2
  },
  {
    "_id": "58c665588b6aa52311afa02c",
    "name_one": "Студия",
    "name": "Студии",
    "crm_id": 0
  },
  {
    "_id": "58c665588b6aa52311afa039",
    "name_one": "Таунхаус",
    "name": "Таунхаусы",
    "crm_id": 40
  },
  {
    "_id": "59b79a3fc775b4f0d776ecda",
    "name_one": "Своб. план.",
    "name": "Своб. план.",
    "crm_id": 60
  },
  {
    "_id": "58c665588b6aa52311afa02f",
    "name_one": "3-к.кв",
    "name": "3-к.кв",
    "crm_id": 3
  },
  {
    "_id": "58c665588b6aa52311afa030",
    "name_one": "4-к.кв",
    "name": "4-к.кв",
    "crm_id": 4
  },
  {
    "_id": "58c665588b6aa52311afa032",
    "name_one": "6-к.кв",
    "name": "6-к.кв",
    "crm_id": 6
  },
  {
    "_id": "6423fe037f8ed055120cf0c5",
    "crm_id": 1008,
    "name": "7 спален",
    "name_one": "7 спален"
  },
  {
    "_id": "6423fe037f8ed055120cf0c3",
    "crm_id": 1006,
    "name": "5 спален",
    "name_one": "5 спален"
  },
  {
    "_id": "6423fe037f8ed055120cf0c2",
    "crm_id": 1005,
    "name": "4 спальни",
    "name_one": "4 спальни"
  },
  {
    "_id": "6423fe037f8ed055120cf0c4",
    "crm_id": 1007,
    "name": "6 спален",
    "name_one": "6 спален"
  },
  {
    "_id": "6423fe037f8ed055120cf0c6",
    "crm_id": 1009,
    "name": "8 спален",
    "name_one": "8 спален"
  },
  {
    "_id": "6423fe037f8ed055120cf0c8",
    "crm_id": 1011,
    "name": "10 спален",
    "name_one": "10 спален"
  },
  {
    "_id": "58c665588b6aa52311afa035",
    "name_one": "3Е-к.кв",
    "name": "3Е-к.кв",
    "crm_id": 23
  },
  {
    "_id": "6423fe037f8ed055120cf0bf",
    "crm_id": 1002,
    "name": "1 спальня",
    "name_one": "1 спальня"
  },
  {
    "_id": "58c665588b6aa52311afa037",
    "name_one": "5Е-к.кв",
    "name": "5Е-к.кв",
    "crm_id": 25
  },
  {
    "_id": "58ca59ea9821282a705f122b",
    "name_one": "1Е-к.кв",
    "name": "1Е-к.кв",
    "crm_id": 35
  },
  {
    "_id": "58c665588b6aa52311afa031",
    "name_one": "5-к.кв",
    "name": "5-к.кв",
    "crm_id": 5
  },
  {
    "_id": "58c665588b6aa52311afa036",
    "name_one": "4Е-к.кв",
    "name": "4Е-к.кв",
    "crm_id": 24
  },
  {
    "_id": "5b474b9ad12679839b606081",
    "name_one": "Комната",
    "name": "Комнаты",
    "crm_id": 100
  },
  {
    "_id": "6423fe037f8ed055120cf0c0",
    "crm_id": 1003,
    "name": "2 спальни",
    "name_one": "2 спальни"
  },
  {
    "_id": "58c665588b6aa52311afa038",
    "name_one": "Коттедж",
    "name": "Коттеджи",
    "crm_id": 30
  },
  {
    "_id": "6423fe037f8ed055120cf0c1",
    "crm_id": 1004,
    "name": "3 спальни",
    "name_one": "3 спальни"
  },
  {
    "_id": "6423fe037f8ed055120cf0c7",
    "crm_id": 1010,
    "name": "9 спален",
    "name_one": "9 спален"
  },
  {
    "_id": "58c665588b6aa52311afa033",
    "name_one": "7-к.кв",
    "name": "7-к.кв",
    "crm_id": 7
  }
]